yasoo/__init__.py
yasoo/constants.py
yasoo/data_fixer.py
yasoo/default_customs.py
yasoo/deserialization.py
yasoo/objects.py
yasoo/serialization.py
yasoo/typing.py
yasoo/utils.py
yasoo-0.12.6.dist-info/LICENSE
yasoo-0.12.6.dist-info/METADATA
yasoo-0.12.6.dist-info/WHEEL
yasoo-0.12.6.dist-info/top_level.txt
yasoo-0.12.6.dist-info/RECORD
