Metadata-Version: 2.1
Name: yasoo
Version: 0.12.6
Summary: Yet another serializer of objects
Home-page: https://github.com/drorvinkler/yasoo
Author: Dror A. Vinkler
License: MIT
Platform: UNKNOWN
Classifier: Programming Language :: Python :: 3
Classifier: License :: OSI Approved :: MIT License
Classifier: Operating System :: OS Independent
Requires-Python: >=3.6
License-File: LICENSE
Requires-Dist: attrs (>=16.2)
Requires-Dist: more-itertools
